dissy/__init__.py
dissy/__main__.py
dissy/app.css
dissy/app.py
dissy/disassemblers/__init__.py
dissy/disassemblers/python.py
dissy/disassemblers/types.py
dissy/disassemblers/x86_64.py
dissy-0.1.0.dist-info/entry_points.txt
dissy-0.1.0.dist-info/LICENSE.md
dissy-0.1.0.dist-info/WHEEL
dissy-0.1.0.dist-info/METADATA
dissy-0.1.0.dist-info/RECORD
